{"cameraMode":{"drawMode":0,"name":"Shaded","section":"Shading Mode"},"sceneLighting":true,"audioPlay":false,"sceneViewState":{"m_AlwaysRefresh":false,"showFog":true,"showSkybox":true,"showFlares":true,"showImageEffects":true,"showParticleSystems":true,"showVisualEffectGraphs":true,"m_FxEnabled":true},"in2DMode":false,"pivot":{"x":-1.8341652154922486,"y":13.125916481018067,"z":-0.5344366431236267},"rotation":{"x":0.5832255482673645,"y":0.03271215036511421,"z":-0.023457232862710954,"w":0.8113726377487183},"size":11.969459533691407,"orthographic":false}